po_translate/__init__.py
po_translate/cli.py
po_translate/translate.py
tests/__init__.py
tests/test_po_translate.py
pofiletranslate-0.5.0.dist-info/LICENCE
pofiletranslate-0.5.0.dist-info/METADATA
pofiletranslate-0.5.0.dist-info/WHEEL
pofiletranslate-0.5.0.dist-info/entry_points.txt
pofiletranslate-0.5.0.dist-info/top_level.txt
pofiletranslate-0.5.0.dist-info/RECORD
