Metadata-Version: 2.2
Name: pofiletranslate
Version: 0.5.0
Summary: A CLI tool for automating PO file translations
Author: Rachid Alassir
Author-email: Rachid Alassir <rachidalassir@gmail.com>
Project-URL: Homepage, https://github.com/RachidAlassir/po-translate
Project-URL: Source, https://github.com/RachidAlassir/po-translate
Project-URL: Tracker, https://github.com/RachidAlassir/po-translate/issues
Keywords: translation,PO files,localization,i18n
Classifier: Development Status :: 4 - Beta
Classifier: Intended Audience :: Developers
Classifier: License :: OSI Approved :: MIT License
Classifier: Programming Language :: Python :: 3
Classifier: Programming Language :: Python :: 3.8
Classifier: Programming Language :: Python :: 3.9
Classifier: Programming Language :: Python :: 3.10
Classifier: Programming Language :: Python :: 3.11
Classifier: Topic :: Software Development :: Internationalization
Classifier: Topic :: Software Development :: Localization
License-File: LICENCE
Requires-Dist: polib
Dynamic: author
